thumos_tai/__init__.py
thumos_tai/config/__init__.py
thumos_tai/config/dataset_config.py
thumos_tai/config/model_config.py
thumos_tai/config/training_config.py
thumos_tai/controller/__init__.py
thumos_tai/controller/tsai_controller.py
thumos_tai/dataset/__init__.py
thumos_tai/dataset/data_reader.py
thumos_tai/dataset/downloader.py
thumos_tai/dataset/read_csv.py
thumos_tai/dataset/sample_generator.py
thumos_tai/dataset/stock_dataset.py
thumos_tai/dataset/synthetic_generator.py
thumos_tai/types/__init__.py
thumos_tai/types/model_enum.py
thumos_tai/types/transform.py
Thumos_TAI-0.0.7.dist-info/METADATA
Thumos_TAI-0.0.7.dist-info/WHEEL
Thumos_TAI-0.0.7.dist-info/top_level.txt
Thumos_TAI-0.0.7.dist-info/RECORD
